tests/__init__.py
tests/config.py
tests/test_api.py
tests/test_asyncclient.py
tests/test_auth.py
tests/test_client.py
tests/test_cursors.py
tests/test_rate_limit.py
tests/test_resultset.py
tests/test_utils.py
tests/tweepy_mastodon/__init__.py
tests/tweepy_mastodon/test_api.py
tests/tweepy_mastodon/test_auth.py
tests/tweepy_mastodon/test_example_usage.py
tests/tweepy_mastodon/test_utils.py
tweepy_mastodon/__init__.py
tweepy_mastodon/api.py
tweepy_mastodon/auth.py
tweepy_mastodon/cache.py
tweepy_mastodon/client.py
tweepy_mastodon/cursor.py
tweepy_mastodon/direct_message_event.py
tweepy_mastodon/errors.py
tweepy_mastodon/list.py
tweepy_mastodon/media.py
tweepy_mastodon/mixins.py
tweepy_mastodon/models.py
tweepy_mastodon/pagination.py
tweepy_mastodon/parsers.py
tweepy_mastodon/place.py
tweepy_mastodon/poll.py
tweepy_mastodon/space.py
tweepy_mastodon/streaming.py
tweepy_mastodon/tweet.py
tweepy_mastodon/user.py
tweepy_mastodon/utils.py
tweepy_mastodon/asynchronous/__init__.py
tweepy_mastodon/asynchronous/client.py
tweepy_mastodon/asynchronous/pagination.py
tweepy_mastodon/asynchronous/streaming.py
tweepy_mastodon/tweepy/__init__.py
tweepy_mastodon/tweepy/api.py
tweepy_mastodon/tweepy/auth.py
tweepy_mastodon/tweepy/utils.py
tweepy_mastodon-0.6.0.dist-info/LICENSE
tweepy_mastodon-0.6.0.dist-info/METADATA
tweepy_mastodon-0.6.0.dist-info/WHEEL
tweepy_mastodon-0.6.0.dist-info/top_level.txt
tweepy_mastodon-0.6.0.dist-info/zip-safe
tweepy_mastodon-0.6.0.dist-info/RECORD
