Metadata-Version: 2.1
Name: tweepy-mastodon
Version: 0.6.0
Summary: Mastodon library with Tweepy interface for Python
Home-page: https://github.com/shuuji3/tweepy-mastodon
Download-URL: https://pypi.org/project/tweepy-mastodon/
Author: TAKAHASHI Shuuji
Author-email: shuuji3@gmail.com
License: MIT
Project-URL: Documentation, https://github.com/shuuji3/tweepy-mastodon
Project-URL: Issue Tracker, https://github.com/shuuji3/tweepy-mastodon/issues
Project-URL: Source Code, https://github.com/shuuji3/tweepy-mastodon
Keywords: mastodon library
Classifier: Development Status :: 5 - Production/Stable
Classifier: Topic :: Software Development :: Libraries
Classifier: License :: OSI Approved :: MIT License
Classifier: Operating System :: OS Independent
Classifier: Programming Language :: Python
Classifier: Programming Language :: Python :: 3
Classifier: Programming Language :: Python :: 3.7
Classifier: Programming Language :: Python :: 3.8
Classifier: Programming Language :: Python :: 3.9
Classifier: Programming Language :: Python :: 3.10
Classifier: Programming Language :: Python :: 3.11
Classifier: Programming Language :: Python :: 3 :: Only
Requires-Python: >=3.7
License-File: LICENSE
Requires-Dist: Mastodon.py (<2,>=1.8.0)
Requires-Dist: tweepy (<5,>=4.12.1)
Provides-Extra: async
Requires-Dist: aiohttp (<4,>=3.7.3) ; extra == 'async'
Requires-Dist: async-lru (<2,>=1.0.3) ; extra == 'async'
Provides-Extra: dev
Requires-Dist: coverage (>=4.4.2) ; extra == 'dev'
Requires-Dist: coveralls (>=2.1.0) ; extra == 'dev'
Requires-Dist: tox (>=3.21.0) ; extra == 'dev'
Requires-Dist: pytest (>=7.2.1) ; extra == 'dev'
Requires-Dist: pytest-mock (>=3.10.0) ; extra == 'dev'
Provides-Extra: docs
Requires-Dist: myst-parser (==0.15.2) ; extra == 'docs'
Requires-Dist: readthedocs-sphinx-search (==0.1.1) ; extra == 'docs'
Requires-Dist: sphinx (==4.2.0) ; extra == 'docs'
Requires-Dist: sphinx-hoverxref (==0.7b1) ; extra == 'docs'
Requires-Dist: sphinx-tabs (==3.2.0) ; extra == 'docs'
Requires-Dist: sphinx-rtd-theme (==1.0.0) ; extra == 'docs'
Provides-Extra: socks
Requires-Dist: requests[socks] (<3,>=2.27.0) ; extra == 'socks'
Provides-Extra: test
Requires-Dist: vcrpy (>=1.10.3) ; extra == 'test'
